cdk_cloudformation_tf_pagerduty_service/__init__.py
cdk_cloudformation_tf_pagerduty_service/py.typed
cdk_cloudformation_tf_pagerduty_service/_jsii/__init__.py
cdk_cloudformation_tf_pagerduty_service/_jsii/tf-pagerduty-service@1.0.0-alpha.7.jsii.tgz
cdk_cloudformation_tf_pagerduty_service-1.0.0a7.dist-info/LICENSE
cdk_cloudformation_tf_pagerduty_service-1.0.0a7.dist-info/METADATA
cdk_cloudformation_tf_pagerduty_service-1.0.0a7.dist-info/WHEEL
cdk_cloudformation_tf_pagerduty_service-1.0.0a7.dist-info/top_level.txt
cdk_cloudformation_tf_pagerduty_service-1.0.0a7.dist-info/RECORD
